{
    "parent": "block/cube_all",
	"textures": {
		"1": "superslegend:block/bush_block",
		"particle": "superslegend:block/bush_block"
	},
	"elements": [
		{
			"from": [6.5, 0, 6.5],
			"to": [9.5, 9, 9.5],
			"rotation": {"angle": 0, "axis": "y", "origin": [15, 10, 15]},
			"faces": {
				"north": {"uv": [0.375, 0.375, 0.75, 1.5], "texture": "#1"},
				"east": {"uv": [0, 0.375, 0.375, 1.5], "texture": "#1"},
				"south": {"uv": [1.125, 0.375, 1.5, 1.5], "texture": "#1"},
				"west": {"uv": [0.75, 0.375, 1.125, 1.5], "texture": "#1"},
				"up": {"uv": [0.75, 0.375, 0.375, 0], "texture": "#1"},
				"down": {"uv": [1.125, 0, 0.75, 0.375], "texture": "#1"}
			}
		},
		{
			"from": [7.25, 9, 7.25],
			"to": [8.75, 14.25, 8.75],
			"rotation": {"angle": 0, "axis": "y", "origin": [8, 13, 8]},
			"faces": {
				"north": {"uv": [0.875, 2.875, 1, 3.5], "texture": "#1"},
				"east": {"uv": [0.75, 2.875, 0.875, 3.5], "texture": "#1"},
				"south": {"uv": [1.125, 2.875, 1.25, 3.5], "texture": "#1"},
				"west": {"uv": [1, 2.875, 1.125, 3.5], "texture": "#1"},
				"up": {"uv": [1, 2.875, 0.875, 2.75], "texture": "#1"},
				"down": {"uv": [1.125, 2.75, 1, 2.875], "texture": "#1"}
			}
		},
		{
			"from": [6.25, 13, 6.25],
			"to": [9.75, 13.5, 9.75],
			"rotation": {"angle": 0, "axis": "y", "origin": [8, 15, 8]},
			"faces": {
				"north": {"uv": [0.375, 2.625, 0.75, 2.75], "texture": "#1"},
				"east": {"uv": [0, 2.625, 0.375, 2.75], "texture": "#1"},
				"south": {"uv": [1.125, 2.625, 1.5, 2.75], "texture": "#1"},
				"west": {"uv": [0.75, 2.625, 1.125, 2.75], "texture": "#1"},
				"up": {"uv": [0.75, 2.625, 0.375, 2.25], "texture": "#1"},
				"down": {"uv": [1.125, 2.25, 0.75, 2.625], "texture": "#1"}
			}
		},
		{
			"from": [5.25, 4.5, 5.25],
			"to": [10.75, 5, 10.75],
			"rotation": {"angle": 0, "axis": "y", "origin": [8, 6.5, 8]},
			"faces": {
				"north": {"uv": [6.625, 4, 7.25, 4.125], "texture": "#1"},
				"east": {"uv": [6, 4, 6.625, 4.125], "texture": "#1"},
				"south": {"uv": [7.875, 4, 8.5, 4.125], "texture": "#1"},
				"west": {"uv": [7.25, 4, 7.875, 4.125], "texture": "#1"},
				"up": {"uv": [7.25, 4, 6.625, 3.375], "texture": "#1"},
				"down": {"uv": [7.875, 3.375, 7.25, 4], "texture": "#1"}
			}
		},
		{
			"from": [5.5, 4, 5.5],
			"to": [10.5, 4.5, 10.5],
			"rotation": {"angle": 0, "axis": "y", "origin": [8, 6, 8]},
			"faces": {
				"north": {"uv": [6.125, 6.75, 6.75, 6.875], "texture": "#1"},
				"east": {"uv": [5.5, 6.75, 6.125, 6.875], "texture": "#1"},
				"south": {"uv": [7.375, 6.75, 8, 6.875], "texture": "#1"},
				"west": {"uv": [6.75, 6.75, 7.375, 6.875], "texture": "#1"},
				"up": {"uv": [6.75, 6.75, 6.125, 6.125], "texture": "#1"},
				"down": {"uv": [7.375, 6.125, 6.75, 6.75], "texture": "#1"}
			}
		},
		{
			"from": [5.5, 5, 5.5],
			"to": [10.5, 8.5, 10.5],
			"rotation": {"angle": 0, "axis": "y", "origin": [8, 7, 8]},
			"faces": {
				"north": {"uv": [0.625, 6.25, 1.25, 6.625], "texture": "#1"},
				"east": {"uv": [0, 6.25, 0.625, 6.625], "texture": "#1"},
				"south": {"uv": [1.875, 6.25, 2.5, 6.625], "texture": "#1"},
				"west": {"uv": [1.25, 6.25, 1.875, 6.625], "texture": "#1"},
				"up": {"uv": [1.25, 6.25, 0.625, 5.625], "texture": "#1"},
				"down": {"uv": [1.875, 5.625, 1.25, 6.25], "texture": "#1"}
			}
		},
		{
			"from": [5.75, 3.5, 5.75],
			"to": [10.25, 4, 10.25],
			"rotation": {"angle": 0, "axis": "y", "origin": [8, 5.5, 8]},
			"faces": {
				"north": {"uv": [5, 3.875, 5.5, 4], "texture": "#1"},
				"east": {"uv": [4.5, 3.875, 5, 4], "texture": "#1"},
				"south": {"uv": [6, 3.875, 6.5, 4], "texture": "#1"},
				"west": {"uv": [5.5, 3.875, 6, 4], "texture": "#1"},
				"up": {"uv": [5.5, 3.875, 5, 3.375], "texture": "#1"},
				"down": {"uv": [6, 3.375, 5.5, 3.875], "texture": "#1"}
			}
		},
		{
			"from": [5.275, 10.275, 5.25],
			"to": [10.75, 10.775, 10.75],
			"rotation": {"angle": 0, "axis": "y", "origin": [8, 12.5, 8]},
			"faces": {
				"north": {"uv": [6.875, 4.875, 7.5, 5], "texture": "#1"},
				"east": {"uv": [6.25, 4.875, 6.875, 5], "texture": "#1"},
				"south": {"uv": [8.125, 4.875, 8.75, 5], "texture": "#1"},
				"west": {"uv": [7.5, 4.875, 8.125, 5], "texture": "#1"},
				"up": {"uv": [7.5, 4.875, 6.875, 4.25], "texture": "#1"},
				"down": {"uv": [8.125, 4.25, 7.5, 4.875], "texture": "#1"}
			}
		},
		{
			"from": [4.775, 9.775, 4.75],
			"to": [11.25, 10.275, 11.25],
			"rotation": {"angle": 0, "axis": "y", "origin": [8, 12, 8]},
			"faces": {
				"north": {"uv": [5.25, 3.25, 6, 3.375], "texture": "#1"},
				"east": {"uv": [4.5, 3.25, 5.25, 3.375], "texture": "#1"},
				"south": {"uv": [6.75, 3.25, 7.5, 3.375], "texture": "#1"},
				"west": {"uv": [6, 3.25, 6.75, 3.375], "texture": "#1"},
				"up": {"uv": [6, 3.25, 5.25, 2.5], "texture": "#1"},
				"down": {"uv": [6.75, 2.5, 6, 3.25], "texture": "#1"}
			}
		},
		{
			"from": [6.75, 0, 6.25],
			"to": [9.25, 5, 6.5],
			"rotation": {"angle": 0, "axis": "y", "origin": [15.5, 10, 13.5]},
			"faces": {
				"north": {"uv": [3.125, 2.375, 3.375, 3], "texture": "#1"},
				"east": {"uv": [3, 2.375, 3.125, 3], "texture": "#1"},
				"south": {"uv": [3.5, 2.375, 3.75, 3], "texture": "#1"},
				"west": {"uv": [3.375, 2.375, 3.5, 3], "texture": "#1"},
				"up": {"uv": [3.375, 2.375, 3.125, 2.25], "texture": "#1"},
				"down": {"uv": [3.625, 2.25, 3.375, 2.375], "texture": "#1"}
			}
		},
		{
			"from": [6.75, 0, 9.5],
			"to": [9.25, 5, 9.75],
			"rotation": {"angle": 0, "axis": "y", "origin": [15.5, 10, 16.75]},
			"faces": {
				"north": {"uv": [3, 3.125, 3.25, 3.75], "texture": "#1"},
				"east": {"uv": [2.875, 3.125, 3, 3.75], "texture": "#1"},
				"south": {"uv": [3.375, 3.125, 3.625, 3.75], "texture": "#1"},
				"west": {"uv": [3.25, 3.125, 3.375, 3.75], "texture": "#1"},
				"up": {"uv": [3.25, 3.125, 3, 3], "texture": "#1"},
				"down": {"uv": [3.5, 3, 3.25, 3.125], "texture": "#1"}
			}
		},
		{
			"from": [7.25, 0, 6],
			"to": [8.75, 5, 6.25],
			"rotation": {"angle": 0, "axis": "y", "origin": [15.5, 10, 13.25]},
			"faces": {
				"north": {"uv": [4.875, 5, 5, 5.625], "texture": "#1"},
				"east": {"uv": [4.75, 5, 4.875, 5.625], "texture": "#1"},
				"south": {"uv": [5.125, 5, 5.25, 5.625], "texture": "#1"},
				"west": {"uv": [5, 5, 5.125, 5.625], "texture": "#1"},
				"up": {"uv": [5, 5, 4.875, 4.875], "texture": "#1"},
				"down": {"uv": [5.125, 4.875, 5, 5], "texture": "#1"}
			}
		},
		{
			"from": [7.25, 0, 9.75],
			"to": [8.75, 5, 10],
			"rotation": {"angle": 0, "axis": "y", "origin": [15.5, 10, 17]},
			"faces": {
				"north": {"uv": [4.375, 5, 4.5, 5.625], "texture": "#1"},
				"east": {"uv": [4.25, 5, 4.375, 5.625], "texture": "#1"},
				"south": {"uv": [4.625, 5, 4.75, 5.625], "texture": "#1"},
				"west": {"uv": [4.5, 5, 4.625, 5.625], "texture": "#1"},
				"up": {"uv": [4.5, 5, 4.375, 4.875], "texture": "#1"},
				"down": {"uv": [4.625, 4.875, 4.5, 5], "texture": "#1"}
			}
		},
		{
			"from": [9.5, 0, 6.75],
			"to": [9.75, 5, 9.25],
			"rotation": {"angle": 0, "axis": "y", "origin": [16.75, 10, 15.5]},
			"faces": {
				"north": {"uv": [0.25, 3, 0.375, 3.625], "texture": "#1"},
				"east": {"uv": [0, 3, 0.25, 3.625], "texture": "#1"},
				"south": {"uv": [0.625, 3, 0.75, 3.625], "texture": "#1"},
				"west": {"uv": [0.375, 3, 0.625, 3.625], "texture": "#1"},
				"up": {"uv": [0.375, 3, 0.25, 2.75], "texture": "#1"},
				"down": {"uv": [0.5, 2.75, 0.375, 3], "texture": "#1"}
			}
		},
		{
			"from": [6.25, 0, 6.75],
			"to": [6.5, 5, 9.25],
			"rotation": {"angle": 0, "axis": "y", "origin": [13.5, 10, 15.5]},
			"faces": {
				"north": {"uv": [2.5, 2.5, 2.625, 3.125], "texture": "#1"},
				"east": {"uv": [2.25, 2.5, 2.5, 3.125], "texture": "#1"},
				"south": {"uv": [2.875, 2.5, 3, 3.125], "texture": "#1"},
				"west": {"uv": [2.625, 2.5, 2.875, 3.125], "texture": "#1"},
				"up": {"uv": [2.625, 2.5, 2.5, 2.25], "texture": "#1"},
				"down": {"uv": [2.75, 2.25, 2.625, 2.5], "texture": "#1"}
			}
		},
		{
			"from": [9.75, 0, 7.25],
			"to": [10, 5, 8.75],
			"rotation": {"angle": 0, "axis": "y", "origin": [17, 10, 15.5]},
			"faces": {
				"north": {"uv": [3.875, 5, 4, 5.625], "texture": "#1"},
				"east": {"uv": [3.75, 5, 3.875, 5.625], "texture": "#1"},
				"south": {"uv": [4.125, 5, 4.25, 5.625], "texture": "#1"},
				"west": {"uv": [4, 5, 4.125, 5.625], "texture": "#1"},
				"up": {"uv": [4, 5, 3.875, 4.875], "texture": "#1"},
				"down": {"uv": [4.125, 4.875, 4, 5], "texture": "#1"}
			}
		},
		{
			"from": [6, 0, 7.25],
			"to": [6.25, 5, 8.75],
			"rotation": {"angle": 0, "axis": "y", "origin": [13.25, 10, 15.5]},
			"faces": {
				"north": {"uv": [4.625, 2.625, 4.75, 3.25], "texture": "#1"},
				"east": {"uv": [4.5, 2.625, 4.625, 3.25], "texture": "#1"},
				"south": {"uv": [4.875, 2.625, 5, 3.25], "texture": "#1"},
				"west": {"uv": [4.75, 2.625, 4.875, 3.25], "texture": "#1"},
				"up": {"uv": [4.75, 2.625, 4.625, 2.5], "texture": "#1"},
				"down": {"uv": [4.875, 2.5, 4.75, 2.625], "texture": "#1"}
			}
		},
		{
			"from": [6.14645, 5.75, 0.89645],
			"to": [9.14645, 8.75, 7.89645],
			"rotation": {"angle": -22.5, "axis": "x", "origin": [7.64645, 7, 4.89645]},
			"faces": {
				"north": {"uv": [5.5, 5.75, 5.875, 6.125], "texture": "#1"},
				"east": {"uv": [4.625, 5.75, 5.5, 6.125], "texture": "#1"},
				"south": {"uv": [6.75, 5.75, 7.125, 6.125], "texture": "#1"},
				"west": {"uv": [5.875, 5.75, 6.75, 6.125], "texture": "#1"},
				"up": {"uv": [5.875, 5.75, 5.5, 4.875], "texture": "#1"},
				"down": {"uv": [6.25, 4.875, 5.875, 5.75], "texture": "#1"}
			}
		},
		{
			"from": [6.14645, 5.75, 8.14645],
			"to": [9.14645, 8.75, 15.14645],
			"rotation": {"angle": 22.5, "axis": "x", "origin": [7.64645, 6.75, 11.14645]},
			"faces": {
				"north": {"uv": [3, 5.75, 3.375, 6.125], "texture": "#1"},
				"east": {"uv": [2.125, 5.75, 3, 6.125], "texture": "#1"},
				"south": {"uv": [4.25, 5.75, 4.625, 6.125], "texture": "#1"},
				"west": {"uv": [3.375, 5.75, 4.25, 6.125], "texture": "#1"},
				"up": {"uv": [3.375, 5.75, 3, 4.875], "texture": "#1"},
				"down": {"uv": [3.75, 4.875, 3.375, 5.75], "texture": "#1"}
			}
		},
		{
			"from": [-1.10355, 5, 3.14645],
			"to": [14.39645, 8, 6.14645],
			"rotation": {"angle": 45, "axis": "y", "origin": [11.39645, 6, 4.64645]},
			"faces": {
				"north": {"uv": [3, 0.375, 4.875, 0.75], "texture": "#1"},
				"east": {"uv": [2.625, 0.375, 3, 0.75], "texture": "#1"},
				"south": {"uv": [5.25, 0.375, 7.125, 0.75], "texture": "#1"},
				"west": {"uv": [4.875, 0.375, 5.25, 0.75], "texture": "#1"},
				"up": {"uv": [4.875, 0.375, 3, 0], "texture": "#1"},
				"down": {"uv": [6.75, 0, 4.875, 0.375], "texture": "#1"}
			}
		},
		{
			"from": [1.39645, 10.75, 3.14645],
			"to": [11.39645, 13.025, 6.14645],
			"rotation": {"angle": 45, "axis": "y", "origin": [11.39645, 11.75, 4.64645]},
			"faces": {
				"north": {"uv": [3.625, 4.625, 4.875, 4.875], "texture": "#1"},
				"east": {"uv": [3.25, 4.625, 3.625, 4.875], "texture": "#1"},
				"south": {"uv": [5.25, 4.625, 6.5, 4.875], "texture": "#1"},
				"west": {"uv": [4.875, 4.625, 5.25, 4.875], "texture": "#1"},
				"up": {"uv": [4.875, 4.625, 3.625, 4.25], "texture": "#1"},
				"down": {"uv": [6.125, 4.25, 4.875, 4.625], "texture": "#1"}
			}
		},
		{
			"from": [9.36091, 10.425, 6.68198],
			"to": [15.36091, 12.7, 9.68198],
			"rotation": {"angle": -22.5, "axis": "z", "origin": [10.36091, 11.5625, 8.18198]},
			"faces": {
				"north": {"uv": [7.125, 0.75, 7.875, 1], "texture": "#1"},
				"east": {"uv": [6.75, 0.75, 7.125, 1], "texture": "#1"},
				"south": {"uv": [8.25, 0.75, 9, 1], "texture": "#1"},
				"west": {"uv": [7.875, 0.75, 8.25, 1], "texture": "#1"},
				"up": {"uv": [7.875, 0.75, 7.125, 0.375], "texture": "#1"},
				"down": {"uv": [8.625, 0.375, 7.875, 0.75], "texture": "#1"}
			}
		},
		{
			"from": [0.45867, 9.65963, 6.68198],
			"to": [6.45867, 11.93463, 9.68198],
			"rotation": {"angle": 22.5, "axis": "z", "origin": [3.45867, 10.79713, 8.18198]},
			"faces": {
				"north": {"uv": [6.625, 5.375, 7.375, 5.625], "texture": "#1"},
				"east": {"uv": [6.25, 5.375, 6.625, 5.625], "texture": "#1"},
				"south": {"uv": [7.75, 5.375, 8.5, 5.625], "texture": "#1"},
				"west": {"uv": [7.375, 5.375, 7.75, 5.625], "texture": "#1"},
				"up": {"uv": [7.375, 5.375, 6.625, 5], "texture": "#1"},
				"down": {"uv": [8.125, 5, 7.375, 5.375], "texture": "#1"}
			}
		},
		{
			"from": [6.36091, 10.4, 9.68198],
			"to": [9.36091, 12.675, 15.68198],
			"rotation": {"angle": 22.5, "axis": "x", "origin": [7.86091, 11.5375, 10.68198]},
			"faces": {
				"north": {"uv": [4.75, 6.875, 5.125, 7.125], "texture": "#1"},
				"east": {"uv": [4, 6.875, 4.75, 7.125], "texture": "#1"},
				"south": {"uv": [5.875, 6.875, 6.25, 7.125], "texture": "#1"},
				"west": {"uv": [5.125, 6.875, 5.875, 7.125], "texture": "#1"},
				"up": {"uv": [5.125, 6.875, 4.75, 6.125], "texture": "#1"},
				"down": {"uv": [5.5, 6.125, 5.125, 6.875], "texture": "#1"}
			}
		},
		{
			"from": [6.36091, 8.9, 0.93198],
			"to": [9.36091, 11.175, 6.93198],
			"rotation": {"angle": -22.5, "axis": "x", "origin": [7.86091, 10.0375, 1.93198]},
			"faces": {
				"north": {"uv": [2.5, 6.875, 2.875, 7.125], "texture": "#1"},
				"east": {"uv": [1.75, 6.875, 2.5, 7.125], "texture": "#1"},
				"south": {"uv": [3.625, 6.875, 4, 7.125], "texture": "#1"},
				"west": {"uv": [2.875, 6.875, 3.625, 7.125], "texture": "#1"},
				"up": {"uv": [2.875, 6.875, 2.5, 6.125], "texture": "#1"},
				"down": {"uv": [3.25, 6.125, 2.875, 6.875], "texture": "#1"}
			}
		},
		{
			"from": [2.86091, 10.75, 6.68198],
			"to": [12.86091, 13, 9.68198],
			"rotation": {"angle": -45, "axis": "y", "origin": [7.86091, 12.25, 8.18198]},
			"faces": {
				"north": {"uv": [0.375, 4.625, 1.625, 4.875], "texture": "#1"},
				"east": {"uv": [0, 4.625, 0.375, 4.875], "texture": "#1"},
				"south": {"uv": [2, 4.625, 3.25, 4.875], "texture": "#1"},
				"west": {"uv": [1.625, 4.625, 2, 4.875], "texture": "#1"},
				"up": {"uv": [1.625, 4.625, 0.375, 4.25], "texture": "#1"},
				"down": {"uv": [2.875, 4.25, 1.625, 4.625], "texture": "#1"}
			}
		},
		{
			"from": [10.25, 5, -1.25],
			"to": [13.25, 8, 14.25],
			"rotation": {"angle": 45, "axis": "y", "origin": [11.75, 6, 11.5]},
			"faces": {
				"north": {"uv": [1.875, 1.875, 2.25, 2.25], "texture": "#1"},
				"east": {"uv": [0, 1.875, 1.875, 2.25], "texture": "#1"},
				"south": {"uv": [4.125, 1.875, 4.5, 2.25], "texture": "#1"},
				"west": {"uv": [2.25, 1.875, 4.125, 2.25], "texture": "#1"},
				"up": {"uv": [2.25, 1.875, 1.875, 0], "texture": "#1"},
				"down": {"uv": [2.625, 0, 2.25, 1.875], "texture": "#1"}
			}
		},
		{
			"from": [6.69134, 6.73694, 6.5],
			"to": [15.44134, 9.73694, 9.5],
			"rotation": {"angle": -22.5, "axis": "z", "origin": [8.44134, 8.23694, 8]},
			"faces": {
				"north": {"uv": [6.375, 1.375, 7.375, 1.75], "texture": "#1"},
				"east": {"uv": [6, 1.375, 6.375, 1.75], "texture": "#1"},
				"south": {"uv": [7.75, 1.375, 8.75, 1.75], "texture": "#1"},
				"west": {"uv": [7.375, 1.375, 7.75, 1.75], "texture": "#1"},
				"up": {"uv": [7.375, 1.375, 6.375, 1], "texture": "#1"},
				"down": {"uv": [8.375, 1, 7.375, 1.375], "texture": "#1"}
			}
		},
		{
			"from": [1, 6.025, 6.5],
			"to": [10, 9.025, 9.5],
			"rotation": {"angle": 22.5, "axis": "z", "origin": [6, 7.025, 8]},
			"faces": {
				"north": {"uv": [0.375, 5.25, 1.5, 5.625], "texture": "#1"},
				"east": {"uv": [0, 5.25, 0.375, 5.625], "texture": "#1"},
				"south": {"uv": [1.875, 5.25, 3, 5.625], "texture": "#1"},
				"west": {"uv": [1.5, 5.25, 1.875, 5.625], "texture": "#1"},
				"up": {"uv": [1.5, 5.25, 0.375, 4.875], "texture": "#1"},
				"down": {"uv": [2.625, 4.875, 1.5, 5.25], "texture": "#1"}
			}
		},
		{
			"from": [2, 7.775, 8.5],
			"to": [14, 9.775, 11.5],
			"rotation": {"angle": 0, "axis": "y", "origin": [8, 8.275, 10]},
			"faces": {
				"north": {"uv": [4.5, 2.25, 6, 2.5], "texture": "#1"},
				"east": {"uv": [4.125, 2.25, 4.5, 2.5], "texture": "#1"},
				"south": {"uv": [6.375, 2.25, 7.875, 2.5], "texture": "#1"},
				"west": {"uv": [6, 2.25, 6.375, 2.5], "texture": "#1"},
				"up": {"uv": [6, 2.25, 4.5, 1.875], "texture": "#1"},
				"down": {"uv": [7.5, 1.875, 6, 2.25], "texture": "#1"}
			}
		},
		{
			"from": [4.5, 7.775, 2],
			"to": [7.5, 9.75, 14],
			"rotation": {"angle": 0, "axis": "y", "origin": [6, 8.275, 8]},
			"faces": {
				"north": {"uv": [3.75, 4, 4.125, 4.25], "texture": "#1"},
				"east": {"uv": [2.25, 4, 3.75, 4.25], "texture": "#1"},
				"south": {"uv": [5.625, 4, 6, 4.25], "texture": "#1"},
				"west": {"uv": [4.125, 4, 5.625, 4.25], "texture": "#1"},
				"up": {"uv": [4.125, 4, 3.75, 2.5], "texture": "#1"},
				"down": {"uv": [4.5, 2.5, 4.125, 4], "texture": "#1"}
			}
		},
		{
			"from": [8.5, 7.775, 2],
			"to": [11.5, 9.725, 14],
			"rotation": {"angle": 0, "axis": "y", "origin": [10, 8.275, 8]},
			"faces": {
				"north": {"uv": [1.5, 3.75, 1.875, 4], "texture": "#1"},
				"east": {"uv": [0, 3.75, 1.5, 4], "texture": "#1"},
				"south": {"uv": [3.375, 3.75, 3.75, 4], "texture": "#1"},
				"west": {"uv": [1.875, 3.75, 3.375, 4], "texture": "#1"},
				"up": {"uv": [1.875, 3.75, 1.5, 2.25], "texture": "#1"},
				"down": {"uv": [2.25, 2.25, 1.875, 3.75], "texture": "#1"}
			}
		},
		{
			"from": [2, 7.775, 4.5],
			"to": [14, 9.775, 7.5],
			"rotation": {"angle": 0, "axis": "y", "origin": [8, 8.275, 6]},
			"faces": {
				"north": {"uv": [3, 1.125, 4.5, 1.375], "texture": "#1"},
				"east": {"uv": [2.625, 1.125, 3, 1.375], "texture": "#1"},
				"south": {"uv": [4.875, 1.125, 6.375, 1.375], "texture": "#1"},
				"west": {"uv": [4.5, 1.125, 4.875, 1.375], "texture": "#1"},
				"up": {"uv": [4.5, 1.125, 3, 0.75], "texture": "#1"},
				"down": {"uv": [6, 0.75, 4.5, 1.125], "texture": "#1"}
			}
		}
	],
	"display": {}
}